amdnet/__init__.py
amdnet/activations.py
amdnet/callbacks.py
amdnet/evaulateAMDNet.py
amdnet/hierarch_model.py
amdnet/losses.py
amdnet/meta.yaml
amdnet/models.py
amdnet/train_AMDNet.py
amdnet/data/crystal.py
amdnet/data/graph.py
amdnet/data/local_env.py
amdnet/layers/__init__.py
amdnet/layers/graph/__init__.py
amdnet/layers/graph/base.py
amdnet/layers/graph/cgcnn.py
amdnet/layers/graph/megnet.py
amdnet/layers/graph/schnet.py
amdnet/layers/readout/__init__.py
amdnet/layers/readout/linear.py
amdnet/layers/readout/set2set.py
amdnet/tests/test_train_AMDNet.py
amdnet/utils/__init__.py
amdnet/utils/descriptor.py
amdnet/utils/general.py
amdnet/utils/layer.py
amdnet/utils/metrics.py
amdnet/utils/models.py
amdnet/utils/molecule.py
amdnet/utils/preprocessing.py
amdnet-1.0.10.dist-info/entry_points.txt
amdnet-1.0.10.dist-info/LICENSE
amdnet-1.0.10.dist-info/WHEEL
amdnet-1.0.10.dist-info/METADATA
amdnet-1.0.10.dist-info/RECORD
