Metadata-Version: 2.1
Name: amdnet
Version: 1.0.10
Summary: Structure motif-centric learning framework for inorganic crystalline systems.
Author-email: Sandro Hauri <qiminyan@temple.edu>, Sterling Baird <sterling.baird@utah.edu>
Requires-Python: >=3.7,<3.10
Classifier: License :: OSI Approved :: BSD License
Requires-Dist: keras
Requires-Dist: matminer
Requires-Dist: matplotlib
Requires-Dist: networkx
Requires-Dist: pandas
Requires-Dist: pybel
Requires-Dist: pymatgen
Requires-Dist: robocrys
Requires-Dist: scipy
Requires-Dist: tensorflow
Requires-Dist: tqdm
Project-URL: Home, https://github.com/sparks-baird/amdnet
